flaskit/__init__.py
flaskit/app.py
flaskit/cli.py
flaskit/data_loader.py
flaskit/discord.py
flaskit/py.typed
flaskit/watch.py
flaskit/routing/__init__.py
flaskit/routing/route.py
flaskit/templates/__init__.py
flaskit/templates/auth_routes_example.py
flaskit/templates/project_templates.py
flaskit/templates/routes_masonite_style.py
flaskit_love-0.2.4.dist-info/licenses/LICENSE
flaskit_love-0.2.4.dist-info/METADATA
flaskit_love-0.2.4.dist-info/WHEEL
flaskit_love-0.2.4.dist-info/entry_points.txt
flaskit_love-0.2.4.dist-info/top_level.txt
flaskit_love-0.2.4.dist-info/RECORD
