Metadata-Version: 2.4
Name: flaskit-love
Version: 0.2.4
Summary: The Modern Fullstack Love Framework - Build Flask apps with elegance
Author-email: Lovken Olustra <lovken@example.com>
License: MIT
Project-URL: Homepage, https://github.com/lovkenolustra/flaskit
Project-URL: Documentation, https://github.com/lovkenolustra/flaskit#readme
Project-URL: Repository, https://github.com/lovkenolustra/flaskit
Project-URL: Issues, https://github.com/lovkenolustra/flaskit/issues
Keywords: flask,framework,web,api,routing,mvc
Classifier: Development Status :: 3 - Alpha
Classifier: Intended Audience :: Developers
Classifier: License :: OSI Approved :: MIT License
Classifier: Programming Language :: Python :: 3
Classifier: Programming Language :: Python :: 3.8
Classifier: Programming Language :: Python :: 3.9
Classifier: Programming Language :: Python :: 3.10
Classifier: Programming Language :: Python :: 3.11
Classifier: Framework :: Flask
Classifier: Topic :: Software Development :: Libraries :: Application Frameworks
Requires-Python: >=3.8
License-File: LICENSE
Requires-Dist: flask>=2.3.0
Requires-Dist: click>=8.0.0
Requires-Dist: rich>=13.0.0
Requires-Dist: requests>=2.31.0
Requires-Dist: python-dotenv>=1.0.0
Requires-Dist: psutil>=5.9.0
Dynamic: license-file
